django_spectator-15.3.0.dist-info/licenses/LICENSE
spectator/__init__.py
spectator/core/__init__.py
spectator/core/admin.py
spectator/core/app_settings.py
spectator/core/apps.py
spectator/core/factories.py
spectator/core/fields.py
spectator/core/imagegenerators.py
spectator/core/managers.py
spectator/core/models.py
spectator/core/paginator.py
spectator/core/sitemaps.py
spectator/core/utils.py
spectator/core/views.py
spectator/core/migrations/0001_initial.py
spectator/core/migrations/0002_creator_slug.py
spectator/core/migrations/0003_set_creator_slug.py
spectator/core/migrations/0004_auto_20180102_0959.py
spectator/core/migrations/__init__.py
spectator/core/static/spectator-core/css/bootstrap.min.css
spectator/core/static/spectator-core/css/bootstrap.min.css.map
spectator/core/templates/spectator_core/base.html
spectator/core/templates/spectator_core/creator_detail.html
spectator/core/templates/spectator_core/creator_list.html
spectator/core/templates/spectator_core/home.html
spectator/core/templates/spectator_core/admin/detail_thumbnail.html
spectator/core/templates/spectator_core/admin/list_thumbnail.html
spectator/core/templates/spectator_core/includes/card_change_object_link.html
spectator/core/templates/spectator_core/includes/card_chart.html
spectator/core/templates/spectator_core/includes/card_nav.html
spectator/core/templates/spectator_core/includes/chart.html
spectator/core/templates/spectator_core/includes/pager.html
spectator/core/templates/spectator_core/includes/pagination.html
spectator/core/templates/spectator_core/includes/roles.html
spectator/core/templates/spectator_core/includes/roles_list.html
spectator/core/templates/spectator_core/includes/thumbnail_detail.html
spectator/core/templates/spectator_core/includes/thumbnail_list.html
spectator/core/templatetags/__init__.py
spectator/core/templatetags/spectator_core.py
spectator/core/urls/__init__.py
spectator/core/urls/core.py
spectator/core/urls/creators.py
spectator/events/__init__.py
spectator/events/admin.py
spectator/events/apps.py
django_spectator-15.3.0.dist-info/METADATA
django_spectator-15.3.0.dist-info/WHEEL
django_spectator-15.3.0.dist-info/top_level.txt
django_spectator-15.3.0.dist-info/RECORD
