Metadata-Version: 2.4
Name: django-spectator
Version: 15.3.0
Summary: A Django app to track book reading, movie viewing, gig going, play watching, etc.
Author-email: Phil Gyford <phil@gyford.com>
License: The MIT License (MIT)
Project-URL: Changelog, https://github.com/philgyford/django-spectator/blob/main/CHANGELOG.md
Project-URL: Documentation, https://github.com/philgyford/django-spectator/blob/main/README.md
Project-URL: Issues, https://github.com/philgyford/django-spectator/issues
Project-URL: Source Code, https://github.com/philgyford/django-spectator
Keywords: spectator,books,reading,cinema,gigs,theatre,theater
Classifier: Development Status :: 5 - Production/Stable
Classifier: Environment :: Web Environment
Classifier: Framework :: Django
Classifier: Framework :: Django :: 4.2
Classifier: Framework :: Django :: 5.1
Classifier: Framework :: Django :: 5.2
Classifier: Intended Audience :: Developers
Classifier: License :: OSI Approved :: MIT License
Classifier: Natural Language :: English
Classifier: Operating System :: OS Independent
Classifier: Programming Language :: Python
Classifier: Programming Language :: Python :: 3 :: Only
Classifier: Programming Language :: Python :: 3.10
Classifier: Programming Language :: Python :: 3.11
Classifier: Programming Language :: Python :: 3.12
Classifier: Programming Language :: Python :: 3.13
Classifier: Programming Language :: Python :: 3.14
Classifier: Topic :: Internet :: WWW/HTTP
Classifier: Topic :: Internet :: WWW/HTTP :: Dynamic Content
Classifier: Topic :: Software Development :: Libraries
Classifier: Topic :: Software Development :: Libraries :: Python Modules
Requires-Python: >=3.10
License-File: LICENSE
Requires-Dist: Django>=4.2
Requires-Dist: django-imagekit<7.0,>=5.0
Requires-Dist: hashids<1.4,>=1.2.0
Requires-Dist: piexif<2.0,>=1.1.3
Requires-Dist: pillow<13.0,>=10.0.0
Dynamic: license-file
